spell/__init__.py
spell/main.py
spell_assistant-0.1.1.dist-info/licenses/LICENSE.txt
spell_assistant-0.1.1.dist-info/METADATA
spell_assistant-0.1.1.dist-info/WHEEL
spell_assistant-0.1.1.dist-info/top_level.txt
spell_assistant-0.1.1.dist-info/RECORD
