Metadata-Version: 2.4
Name: spell-assistant
Version: 0.1.1
Summary: SpeLL: An expert AI assistant for spectral data modeling and Python code generation. See LICENSE.txt for usage terms.
Home-page: https://github.com/Drjiashun/spell-assistant
Author: Jiashun Fu
Author-email: fujiashun1998@163.com
License: Custom - See LICENSE.txt
Keywords: spell,ai,spectral analysis,chemistry,code generation,rag,llm,llama,assistant
Classifier: Development Status :: 3 - Alpha
Classifier: Intended Audience :: Developers
Classifier: Intended Audience :: Science/Research
Classifier: License :: Other/Proprietary License
Classifier: Operating System :: OS Independent
Classifier: Programming Language :: Python :: 3
Classifier: Programming Language :: Python :: 3.8
Classifier: Programming Language :: Python :: 3.9
Classifier: Programming Language :: Python :: 3.10
Classifier: Programming Language :: Python :: 3.11
Classifier: Programming Language :: Python :: 3.12
Classifier: Topic :: Scientific/Engineering :: Artificial Intelligence
Classifier: Topic :: Scientific/Engineering :: Chemistry
Classifier: Topic :: Software Development :: Libraries :: Python Modules
Requires-Python: >=3.8
License-File: LICENSE.txt
Dynamic: author
Dynamic: author-email
Dynamic: classifier
Dynamic: description
Dynamic: description-content-type
Dynamic: home-page
Dynamic: keywords
Dynamic: license
Dynamic: license-file
Dynamic: requires-python
Dynamic: summary
